lyzr_experimental_automata/__init__.py
lyzr_experimental_automata/automata.py
lyzr_experimental_automata-0.2.1.dist-info/LICENSE
lyzr_experimental_automata-0.2.1.dist-info/METADATA
lyzr_experimental_automata-0.2.1.dist-info/WHEEL
lyzr_experimental_automata-0.2.1.dist-info/top_level.txt
lyzr_experimental_automata-0.2.1.dist-info/RECORD
