Metadata-Version: 2.1
Name: lyzr-experimental-automata
Version: 0.2.1
Summary: A prompt based agent workflow that integrates with other Lyzr agents
Home-page: https://github.com/lyzrcore/lyzr-experimental-automata
Author: Siva Surendira
Author-email: siva@lyzr.ai
License: MIT
License-File: LICENSE
Requires-Dist: openai
Requires-Dist: asyncio
